[
    {
        "dateOfBirth": "2021-09-21",
        "id": "4660a786-ce8d-40e1-b74d-5d2e10f161ed",
        "firstName": "Anonymous",
        "lastName": null,
        "email": null,
        "mobileNumber": "8610631156",
        "latitude": 12.979999,
        "longitude": 80.126028,
        "profileUrl": null,
        "countryCode": "91",
        "isUpdated": false,
        "isVerified": false,
        "verificationId": "test",
        "paymentId": "cus_KdwxgIhpULimLB",
        "createdAt": "2021-09-12T10:38:39.002Z",
        "updatedAt": "2021-09-12T10:38:39.002Z",
        "tierId": 1,
        "tierExpires": "2021-09-12"
    },
    {
        "dateOfBirth": "2021-09-21",
        "id": "4660a786-ce8d-40e1-b74d-5d2e10f161ec",
        "firstName": "Mukesh",
        "lastName": "R",
        "email": "ilmnmukesh@gmail.com",
        "mobileNumber": "8610631155",
        "latitude": 12.979999,
        "longitude": 80.126028,
        "profileUrl": null,
        "countryCode": "91",
        "verificationId": "test",
        "paymentId": "cus_KdwxgIhpULimLB",
        "isUpdated": true,
        "isVerified": true,
        "createdAt": "2021-09-12T10:38:39.002Z",
        "updatedAt": "2021-09-12T10:38:39.002Z",
        "tierId": 1
    },
    {
        "dateOfBirth": "2021-09-21",
        "id": "298c4199-61f2-4496-b67c-d72dab00bef6",
        "firstName": "Mani",
        "lastName": "E",
        "email": "mani@gmail.com",
        "mobileNumber": "9962907052",
        "latitude": 12.979999,
        "longitude": 80.126028,
        "profileUrl": null,
        "countryCode": "91",
        "isUpdated": true,
        "verificationId": "test",
        "paymentId": "cus_KdwxgIhpULimLB",
        "isVerified": true,
        "createdAt": "2021-09-12T10:38:39.002Z",
        "updatedAt": "2021-09-12T10:38:39.002Z",
        "tierId": 1,
        "tierExpires": "2021-09-12"
    },
    {
        "id": "5fd4a331-0dce-47d9-a86f-30d831966c8e",
        "firstName": "Abhi",
        "lastName": "Abhi",
        "email": "Abhifriend08@gmail.com",
        "mobileNumber": "9599552851",
        "dateOfBirth": "1984-10-08",
        "latitude": null,
        "longitude": null,
        "profileUrl": null,
        "countryCode": "91",
        "isUpdated": true,
        "isVerified": true,
        "paymentId": "cus_KgnrWqddJ9OaDH",
        "verificationId": "LBX9QbmT7fReonzctwEd0UITEES4v14s",
        "verificationExpires": "2021-11-30T06:54:42.711Z",
        "createdAt": "2021-11-30T06:43:45.028Z",
        "updatedAt": "2021-11-30T06:56:12.201Z",
        "tierId": 1,
        "tierExpires": "2021-09-12"
    },
    {
        "id": "eab8d88f-c8b6-43f1-8d5d-5b8863c3a677",
        "firstName": "Saurabh",
        "lastName": "Gupta",
        "email": "tosaurabh1@gmail.com",
        "mobileNumber": "4803526281",
        "dateOfBirth": "1982-12-20",
        "latitude": null,
        "longitude": null,
        "profileUrl": null,
        "countryCode": "91",
        "isUpdated": true,
        "isVerified": true,
        "paymentId": "cus_KgnsWdTGdrvIfR",
        "verificationId": "6JlD0HnaRhrDlj6lajKDtVZV6fKHtvgQ",
        "verificationExpires": "2021-11-30T06:45:56.063Z",
        "createdAt": "2021-11-30T06:44:48.654Z",
        "updatedAt": "2021-11-30T06:56:29.570Z",
        "tierId": 1,
        "tierExpires": "2021-09-12"
    },
    {
        "id": "72a9782e-efe5-43a5-b043-7722cb69f004",
        "firstName": "A",
        "lastName": "B",
        "email": "A@gmail.com",
        "mobileNumber": "9876543211",
        "dateOfBirth": "1982-12-20",
        "latitude": null,
        "longitude": null,
        "profileUrl": null,
        "countryCode": "91",
        "isUpdated": true,
        "isVerified": false,
        "paymentId": "cus_KgnsWdTGdrvIfR",
        "verificationId": "6JlD0HnaRhrDlj6lajKDtVZV6fKHtvgQ",
        "verificationExpires": "2021-11-30T06:45:56.063Z",
        "createdAt": "2021-11-30T06:44:48.654Z",
        "updatedAt": "2021-11-30T06:56:29.570Z",
        "tierId": 1,
        "tierExpires": "2021-09-12"
    },
    {
        "id": "834d1b69-78a8-4bdc-9709-a908389938eb",
        "firstName": "Aa",
        "lastName": "Bb",
        "email": "B@gmail.com",
        "mobileNumber": "9876543210",
        "dateOfBirth": "1982-12-20",
        "latitude": null,
        "longitude": null,
        "profileUrl": null,
        "countryCode": "91",
        "isUpdated": true,
        "isVerified": true,
        "paymentId": "cus_KgnsWdTGdrvIfR",
        "verificationId": "6JlD0HnaRhrDlj6lajKDtVZV6fKHtvgQ",
        "verificationExpires": "2021-11-30T06:45:56.063Z",
        "createdAt": "2021-11-30T06:44:48.654Z",
        "updatedAt": "2021-11-30T06:56:29.570Z",
        "tierId": 1,
        "tierExpires": "2021-09-12"
    }
]
